cadurso/__init__.py
cadurso/errors.py
cadurso/exceptions.py
cadurso/py.typed
cadurso/sugar.py
cadurso/system.py
cadurso/type_aliases.py
cadurso-0.6.0.dist-info/METADATA
cadurso-0.6.0.dist-info/WHEEL
cadurso-0.6.0.dist-info/RECORD
