Metadata-Version: 2.4
Name: cadurso
Version: 0.6.0
Summary: Authorization framework for Python-based applications
Project-URL: homepage, https://github.com/flipbit03/cadurso
Project-URL: source, https://github.com/flipbit03/cadurso
Project-URL: issues, https://github.com/flipbit03/cadurso/issues
Author-email: cadu <cadu.coelho@gmail.com>
License-Expression: MIT
Classifier: Development Status :: 5 - Production/Stable
Classifier: Programming Language :: Python :: 3.11
Classifier: Programming Language :: Python :: 3.12
Classifier: Programming Language :: Python :: 3.13
Classifier: Programming Language :: Python :: 3.14
Classifier: Typing :: Typed
Requires-Python: >=3.11
